[
  {
    "id": 1,
    "label": "Cámaras",
    "path": "/categoria/camaras",
    "img": "/categorias/camaras.png"
  },
  {
    "id": 2,
    "label": "Lentes",
    "path": "/categoria/lentes",
    "img": "/categorias/lentes.png"
  },
  {
    "id": 3,
    "label": "Luces",
    "path": "/categoria/luces",
    "img": "/categorias/luces.png"
  },
  {
    "id": 4,
    "label": "Audio",
    "path": "/categoria/audio",
    "img": "/categorias/audio.png"
  },
  {
    "id": 5,
    "label": "Profesionales",
    "path": "/categoria/profesionales",
    "img": "/categorias/profesionales.png"
  }
]